absolute_math.py
absolute_math-0.1.0.dist-info/METADATA
absolute_math-0.1.0.dist-info/WHEEL
absolute_math-0.1.0.dist-info/top_level.txt
absolute_math-0.1.0.dist-info/RECORD
