Metadata-Version: 2.4
Name: absolute_math
Version: 0.1.0
Summary: Python module that tests number characters with symbolic passages
Author: MODUPY
Requires-Python: >=3.8
Requires-Dist: sympy>=1.12
